<PAMDataset>
  <PAMRasterBand band="1">
    <Histograms>
      <HistItem>
        <HistMin>80</HistMin>
        <HistMax>14241</HistMax>
        <BucketCount>256</BucketCount>
        <IncludeOutOfRange>1</IncludeOutOfRange>
        <Approximate>0</Approximate>
        <HistCounts>107|1126|5249|31783|98648|119928|88981|72344|61352|64077|67943|79696|91832|89293|71794|57854|47611|39503|34277|29070|26459|24968|25874|25849|25351|25618|25900|23704|22669|20645|19840|17709|15008|12663|10793|8848|7479|6426|4988|3767|2724|2072|1686|1435|1219|976|787|621|564|454|420|369|271|249|231|262|333|326|327|211|190|170|157|160|132|119|87|67|48|46|28|23|15|14|15|16|10|5|5|8|4|8|10|6|6|5|6|4|3|6|4|5|2|3|2|1|0|1|0|3|0|2|0|1|0|1|0|4|0|1|1|1|0|0|2|0|1|2|1|0|1|0|1|1|0|0|0|1|1|0|2|0|0|1|0|0|0|0|0|0|0|0|0|0|1|0|0|1|0|0|0|0|0|0|1|1|0|0|0|0|0|0|0|0|0|0|0|0|0|0|0|0|0|0|0|0|0|0|0|1|0|0|0|0|0|0|0|0|0|0|0|0|1|0|1|2|0|0|0|0|1|0|0|0|0|0|0|0|0|0|0|1|1|0|0|0|0|0|0|0|1|0|0|0|0|1|2|0|0|0|0|0|0|0|0|0|0|0|1|0|1|0|0|0|0|0|0|0|0|0|0|0|0|0|0|1</HistCounts>
      </HistItem>
    </Histograms>
    <Metadata>
      <MDI key="STATISTICS_COVARIANCES">262953.8543468963</MDI>
      <MDI key="STATISTICS_EXCLUDEDVALUES"></MDI>
      <MDI key="STATISTICS_MAXIMUM">14241</MDI>
      <MDI key="STATISTICS_MEAN">904.91106370668</MDI>
      <MDI key="STATISTICS_MEDIAN">746.400000</MDI>
      <MDI key="STATISTICS_MINIMUM">80</MDI>
      <MDI key="STATISTICS_SKIPFACTORX">1</MDI>
      <MDI key="STATISTICS_SKIPFACTORY">1</MDI>
      <MDI key="STATISTICS_STDDEV">512.79026350633</MDI>
    </Metadata>
  </PAMRasterBand>
</PAMDataset>
